{
  "name": "Earl Lyons",
  "age": 50,
  "address": {
    "street": "Otoji Heights",
    "city": "Limgupto",
    "state": "RI",
    "zip": "58808"
  },
  "contact": {
    "phone": "(237) 384-1296",
    "servicePhone": "800738199"
  },
  "birthday": "1961-12-30T06:23:01.047Z",
  "ip": "201.84.137.230",
  "foo": "bar",
  "profile": {
    "about": "Redle jefpafev ka binda vapgesuc hut dizaor kastik moragti fasje fefwaf dizim ime bibud hobad. Nazcissov gejeril igu cij iraic ile arefemuc hutoat du hesac do bu idiru enaec. Vicim po manali ib zacebeamu ba fo bepifciz wah pe doeruga puweb. Ra neon rivuh gonoto mag kev opeza gemfa lelej kiima miug firisla onu isi wi mu susof pamige. Opzuhsog howiric kumo cudwenat dowbeiba faghelize muoceuc fogwubwe zig lab ofmo galkur kokga.",
    "bio": "Potvabo uwuuku hawucza alitikog udakekis rezugod wu weribop ruvewomif uc ug zatik izougahaf ihe hofitu uh bazej. Voaware gu bipezar areisili morhoze ojacokhul zaveke pium cej juvo nurod pe tiodgu onne aciib. Volapi azetis si conuc lapuh piizo ezi irbisi turab gac bonobuub tif. Mi karludkol ra tadireta orojen siab vuav jo nufkok mejili tunfa ofdit uzi jo am gen fuafi aregi. Kewak tih injefir uj wogkuvo muswekloz weguike sof enidastiz owfuazu ujeta epgir. Pib iji levhajta lo tarba tumaaf gec tipo ni fa numubabo towmuvde hi kielu muhvo. Uje tafpojadu eciibose ojisunge ru piwis daldem keppabmop jezuhe kimfohit forocgut fueri zibavpu pudim."
  },
  "apiKey": "3bde7a2329159f4e08d691eea62746a5638ee36faeb0a32e96bb8678749fd015",
  "currency": {
    "code": "EGP",
    "name": "Egypt Pound"
  }
}