{
  "name": "Nell Fletcher",
  "age": 51,
  "address": {
    "street": "Hizebi Turnpike",
    "city": "Ihpave",
    "state": "UT",
    "zip": "26316"
  },
  "contact": {
    "phone": "(922) 356-7272",
    "servicePhone": "800176565"
  },
  "birthday": "1972-02-27T00:37:27.741Z",
  "ip": "15.224.83.187",
  "foo": "bar",
  "profile": {
    "about": "Zeffo wemo mih gindin ziw ovugave riorpi as cogo ojweub rud zu mu wecde posubehec po po. Uwker tukoiji juwurgef cod wosni zos bawi uwena ca govofi jevjohluw lujed. Ilozuma ut malzu ow ropve nu mok gogpas cipded piwur huva weclohoh rute ugopew kinran. Bidem runej admaut ocepatduv fajenocev juserfaf jec vasu wa hecuw lehahci awuewe oseufoon al muchioda mabe.",
    "bio": "Vufej fired udcah ceawu fugutzo wegoga go gojran sa ukenoket ebsooja pa lebbij obuzi. Ko bipripe ona ubuer hogerifo mefiwu ru tug he licte duekilek diswiek ijiigizel ziktadil. Cibezfe te vecagi mu polacdih vuruf akesu dopoklu sakmukcu seidni nokudu mine sicup dula ruas iduzec afu fafet. Zu isna kanbi ezko cib bazarun te evolovjad ejatwar nupuba sinara ebavo ra gele lo lawkaro. No vus ibda uttizev gitjonguj wur gubocgi gocbav zegi ezmopruh se di gedfu hu ru darlug im kelef. Kofus koralo vaikhas sokru iv gor cifikin itoimriv opkokle liizhah calmimuk sun ifitidpon robeni. Kuvva bewevu becus hobpehi ahalakcic wek reone unout nunot jadubdiz cojju pile be ihelozdo zo."
  },
  "apiKey": "bfb36960c66a9bf2894ef876bce80704ef2c2b5ccac3d949212c5d9449b7f07c",
  "currency": {
    "code": "EUR",
    "name": "Euro Member Countries"
  }
}