{
  "name": "Nannie Cohen",
  "age": 59,
  "address": {
    "street": "Maheg Path",
    "city": "Wukcuwwod",
    "state": "KS",
    "zip": "63221"
  },
  "contact": {
    "phone": "(875) 345-7825",
    "servicePhone": "800868321"
  },
  "birthday": "2006-04-03T08:20:20.234Z",
  "ip": "49.33.213.214",
  "foo": "bar",
  "profile": {
    "about": "Asoudi omoevseg om tuzmes pud kifpo wiupe ovvaz herhazit ivegom ceewu modaru van tu comallis. Kit hovpige zofsah pata kiz bunoita kizo ejocag zoh uhomo in dajal nopdikuk. Duwatari wuz codwa pomo omo mukuj gafkuv zudosik uribicwum jesiwuso fibo citalri la gul. Arsu ibuvaf but samcu vagwo hailefec weivaej avlur fa eseah wobekpog rozwumel dihbelcin pecta. Abe doji am meuf kub fegasci ani kujzit lusfuc pefad aliok zo.",
    "bio": "Venolif zu muzowpim kutlivew ificitze ajazozo mefohlin sefomwo apeuve pi cibefe ze ebu. Gafhi fihbav surar sowet otdano ami fojho daw vifeponob tal osmaure pulpebuv uz. Gomazed ebi hufa aw fej mi cit si ku vod vakeus oj abi tem isoz. Jaro so worgi suboibe fuszicnel raksuksa talarih rum wi mojap cuboc boh kimese kekge kus."
  },
  "apiKey": "86a445c484ce10d094fd55645e02a004c93252500597244617a88506d973ae38",
  "currency": {
    "code": "OMR",
    "name": "Oman Rial"
  }
}